funcnodes_pyodide/__init__.py
funcnodes_pyodide/__main__.py
funcnodes_pyodide/patch.py
funcnodes_pyodide/worker.py
funcnodes_pyodide-0.1.11.dist-info/METADATA
funcnodes_pyodide-0.1.11.dist-info/WHEEL
funcnodes_pyodide-0.1.11.dist-info/top_level.txt
funcnodes_pyodide-0.1.11.dist-info/RECORD
