Metadata-Version: 2.4
Name: funcnodes-pyodide
Version: 0.1.11
Summary: Funcnodes in pyodide
License: AGPL-3.0
Classifier: License :: OSI Approved :: GNU Affero General Public License v3 or later (AGPLv3+)
Requires-Python: >=3.11
Requires-Dist: funcnodes>=0.5.36
Requires-Dist: funcnodes-worker>=0.3.1
Requires-Dist: funcnodes_core>=0.3.51
